geometor/divine/__init__.py
geometor/divine/__main__.py
geometor/divine/divine.py
geometor/divine/events.py
geometor/divine/golden/__init__.py
geometor/divine/golden/chains.py
geometor/divine/golden/groups.py
geometor/divine/golden/ranges.py
geometor_divine-0.3.5.dist-info/licenses/LICENSE
geometor_divine-0.3.5.dist-info/METADATA
geometor_divine-0.3.5.dist-info/WHEEL
geometor_divine-0.3.5.dist-info/entry_points.txt
geometor_divine-0.3.5.dist-info/top_level.txt
geometor_divine-0.3.5.dist-info/RECORD
