Metadata-Version: 2.4
Name: geometor-divine
Version: 0.3.5
Summary: An analysis engine for identifying golden sections and harmonic ranges.
Author-email: geometor <github@geometor.com>
Project-URL: Website, https://geometor.github.io/divine
Project-URL: Repository, https://github.com/geometor/divine
Project-URL: Issues, https://github.com/geometor/divine/issues
Classifier: Programming Language :: Python :: 3
Classifier: License :: OSI Approved :: MIT License
Classifier: Operating System :: OS Independent
Requires-Python: >=3.13
License-File: LICENSE
Requires-Dist: geometor-model
Requires-Dist: sympy
Dynamic: license-file
